MANIFEST.in
NEWS.txt
README.rst
setup.py
src/Mars24/__init__.py
src/Mars24.egg-info/PKG-INFO
src/Mars24.egg-info/SOURCES.txt
src/Mars24.egg-info/dependency_links.txt
src/Mars24.egg-info/not-zip-safe
src/Mars24.egg-info/requires.txt
src/Mars24.egg-info/top_level.txt