Metadata-Version: 1.0
Name: Mars24
Version: 0.4.1
Summary: Mars24 wrapper to use marstime
Home-page: UNKNOWN
Author: Christopher Lee
Author-email: lee@foldmountain.com
License: BSD
Platform: UNKNOWN
